cloudsen12/__init__.py
cloudsen12/main.py
cloudsen12/utils.py
cloudsen12-0.0.7.dist-info/LICENSE
cloudsen12-0.0.7.dist-info/METADATA
cloudsen12-0.0.7.dist-info/WHEEL
cloudsen12-0.0.7.dist-info/top_level.txt
cloudsen12-0.0.7.dist-info/RECORD
