Metadata-Version: 2.1
Name: cloudsen12
Version: 0.0.7
Summary: A Python package for use cloudsen12
Home-page: https://github.com/cloudsen12/cloudsen12
Author: Cesar Luis Aybar Camacho
Author-email: csaybar@gmail.com
License: MIT
Classifier: Development Status :: 2 - Pre-Alpha
Classifier: License :: OSI Approved :: MIT License
Classifier: Programming Language :: Python
Classifier: Programming Language :: Python :: 3.6
Classifier: Programming Language :: Python :: 3.7
Classifier: Programming Language :: Python :: 3.8
Classifier: Programming Language :: Python :: 3.9
License-File: LICENSE
Requires-Dist: maskay
Requires-Dist: pytorch-lightning
Requires-Dist: segmentation-models-pytorch
Requires-Dist: gdown
Requires-Dist: pystac
Requires-Dist: dill
Requires-Dist: shapely
